README.md
setup.cfg
setup.py
aswath_math_distributions/Binomialdistribution.py
aswath_math_distributions/Gaussiandistribution.py
aswath_math_distributions/Generaldistribution.py
aswath_math_distributions/__init__.py
aswath_math_distributions.egg-info/PKG-INFO
aswath_math_distributions.egg-info/SOURCES.txt
aswath_math_distributions.egg-info/dependency_links.txt
aswath_math_distributions.egg-info/not-zip-safe
aswath_math_distributions.egg-info/top_level.txt